nitter_scraper/__init__.py
nitter_scraper/nitter.py
nitter_scraper/paths.py
nitter_scraper/profile.py
nitter_scraper/schema.py
nitter_scraper/templates/nitter.conf
nitter_scraper/tweets.py
nitter_scraper-0.5.0.dist-info/LICENSE
nitter_scraper-0.5.0.dist-info/WHEEL
nitter_scraper-0.5.0.dist-info/METADATA
nitter_scraper-0.5.0.dist-info/RECORD
